ellipsize/__about__.py
ellipsize/__init__.py
ellipsize/ellipsize.py
ellipsize-0.3.3.dist-info/METADATA
ellipsize-0.3.3.dist-info/WHEEL
ellipsize-0.3.3.dist-info/licenses/LICENSE.txt
ellipsize-0.3.3.dist-info/RECORD
