Metadata-Version: 2.4
Name: ellipsize
Version: 0.3.3
Summary: Pretty reducing huge Python objects to visualize them nicely.
Project-URL: Homepage, https://andgineer.github.io/ellipsize/
Project-URL: Documentation, https://andgineer.github.io/ellipsize/
Author-email: Andrey Sorokin <andrey@sorokin.engineer>
License: Copyright (c) 2021 Andrey Sorokin <andrey@sorokin.engineer>
License-File: LICENSE.txt
Keywords: ellipsis,log,print
Classifier: License :: OSI Approved :: MIT License
Classifier: Operating System :: OS Independent
Classifier: Programming Language :: Python :: 3
Requires-Python: >=3.8
